[
    {
        "abend": null,
        "id": null,
        "mail": "franziska.anspach@bverwg.bund.de",        
        "name": "",
        "vormittag": "", "nachmittag1": "", "nachmittag2": "",
        "teilnahme": null,
		"fertig":null
    },
    {
        "abend": null,
        "id": null,
        "mail": "Lutz.Barnheim@bverwg.bund.de",        
        "name": "",
        "vormittag": "", "nachmittag1": "", "nachmittag2": "",
        "teilnahme": null,
		"fertig":null
    },
    {
        "abend": null,
        "id": null,
        "mail": "Gabriele.Bech@bverwg.bund.de",        
        "name": "",
        "vormittag": "", "nachmittag1": "", "nachmittag2": "",
        "teilnahme": null,
		"fertig":null
    },
    {
        "abend": null,
        "id": null,
        "mail": "matthias.beiderbeck@bverwg.bund.de",        
        "name": "",
        "vormittag": "", "nachmittag1": "", "nachmittag2": "",
        "teilnahme": null,
		"fertig":null
    },
    {
        "abend": null,
        "id": null,
        "mail": "Uwe-Dietmar.Berlit@bverwg.bund.de",        
        "name": "",
        "vormittag": "", "nachmittag1": "", "nachmittag2": "",
        "teilnahme": null,
		"fertig":null
    },
    {
        "abend": null,
        "id": null,
        "mail": "antje.bettac@bverwg.bund.de",        
        "name": "",
        "vormittag": "", "nachmittag1": "", "nachmittag2": "",
        "teilnahme": null,
		"fertig":null
    },
    {
        "abend": null,
        "id": null,
        "mail": "ulrike.bick@bverwg.bund.de",        
        "name": "",
        "vormittag": "", "nachmittag1": "", "nachmittag2": "",
        "teilnahme": null,
		"fertig":null
    },
    {
        "abend": null,
        "id": null,
        "mail": "Wolfgang.Bier@bverwg.bund.de",        
        "name": "",
        "vormittag": "", "nachmittag1": "", "nachmittag2": "",
        "teilnahme": null,
		"fertig":null
    },
    {
        "abend": null,
        "id": null,
        "mail": "martin.brandt@bverwg.bund.de",        
        "name": "",
        "vormittag": "", "nachmittag1": "", "nachmittag2": "",
        "teilnahme": null,
		"fertig":null
    },
    {
        "abend": null,
        "id": null,
        "mail": "Ines.Braun@bverwg.bund.de",        
        "name": "",
        "vormittag": "", "nachmittag1": "", "nachmittag2": "",
        "teilnahme": null,
		"fertig":null
    },
    {
        "abend": null,
        "id": null,
        "mail": "Aileen.Braun@bverwg.bund.de",        
        "name": "",
        "vormittag": "", "nachmittag1": "", "nachmittag2": "",
        "teilnahme": null,
		"fertig":null
    },
    {
        "abend": null,
        "id": null,
        "mail": "Uwe.Brumma@bverwg.bund.de",        
        "name": "",
        "vormittag": "", "nachmittag1": "", "nachmittag2": "",
        "teilnahme": null,
		"fertig":null
    },
    {
        "abend": null,
        "id": null,
        "mail": "Marlen.Broemler@bverwg.bund.de",        
        "name": "",
        "vormittag": "", "nachmittag1": "", "nachmittag2": "",
        "teilnahme": null,
		"fertig":null
    },
    {
        "abend": null,
        "id": null,
        "mail": "Elisabeth.Buchberger@bverwg.bund.de",        
        "name": "",
        "vormittag": "", "nachmittag1": "", "nachmittag2": "",
        "teilnahme": null,
		"fertig":null
    },
    {
        "abend": null,
        "id": null,
        "mail": "Ulrike.Bumke@bverwg.bund.de",        
        "name": "",
        "vormittag": "", "nachmittag1": "", "nachmittag2": "",
        "teilnahme": null,
		"fertig":null
    },
    {
        "abend": null,
        "id": null,
        "mail": "guenter.burmeister@bverwg.bund.de",        
        "name": "",
        "vormittag": "", "nachmittag1": "", "nachmittag2": "",
        "teilnahme": null,
		"fertig":null
    },
    {
        "abend": null,
        "id": null,
        "mail": "Cornelie.Butz@bverwg.bund.de",        
        "name": "",
        "vormittag": "", "nachmittag1": "", "nachmittag2": "",
        "teilnahme": null,
		"fertig":null
    },
    {
        "abend": null,
        "id": null,
        "mail": "petra.baerhold@bverwg.bund.de",        
        "name": "",
        "vormittag": "", "nachmittag1": "", "nachmittag2": "",
        "teilnahme": null,
		"fertig":null
    },
    {
        "abend": null,
        "id": null,
        "mail": "heike.boehme@bverwg.bund.de",        
        "name": "",
        "vormittag": "", "nachmittag1": "", "nachmittag2": "",
        "teilnahme": null,
		"fertig":null
    },
    {
        "abend": null,
        "id": null,
        "mail": "Marko.Boehme@bverwg.bund.de",        
        "name": "",
        "vormittag": "", "nachmittag1": "", "nachmittag2": "",
        "teilnahme": null,
		"fertig":null
    },
    {
        "abend": null,
        "id": null,
        "mail": "katja.boeker@bverwg.bund.de",        
        "name": "",
        "vormittag": "", "nachmittag1": "", "nachmittag2": "",
        "teilnahme": null,
		"fertig":null
    },
    {
        "abend": null,
        "id": null,
        "mail": "diana.boettger@bverwg.bund.de",        
        "name": "",
        "vormittag": "", "nachmittag1": "", "nachmittag2": "",
        "teilnahme": null,
		"fertig":null
    },
    {
        "abend": null,
        "id": null,
        "mail": "jessica.buettner@bverwg.bund.de",        
        "name": "",
        "vormittag": "", "nachmittag1": "", "nachmittag2": "",
        "teilnahme": null,
		"fertig":null
    },
    {
        "abend": null,
        "id": null,
        "mail": "josef.christ@bverwg.bund.de",        
        "name": "",
        "vormittag": "", "nachmittag1": "", "nachmittag2": "",
        "teilnahme": null,
		"fertig":null
    },
    {
        "abend": null,
        "id": null,
        "mail": "andreas.decker@bverwg.bund.de",        
        "name": "",
        "vormittag": "", "nachmittag1": "", "nachmittag2": "",
        "teilnahme": null,
		"fertig":null
    },
    {
        "abend": null,
        "id": null,
        "mail": "Dieter.Deiseroth@bverwg.bund.de",        
        "name": "",
        "vormittag": "", "nachmittag1": "", "nachmittag2": "",
        "teilnahme": null,
		"fertig":null
    },
    {
        "abend": null,
        "id": null,
        "mail": "Sylke.Dietrich@bverwg.bund.de",        
        "name": "",
        "vormittag": "", "nachmittag1": "", "nachmittag2": "",
        "teilnahme": null,
		"fertig":null
    },
    {
        "abend": null,
        "id": null,
        "mail": "FranzWilhelm.Dollinger@bverwg.bund.de",        
        "name": "",
        "vormittag": "", "nachmittag1": "", "nachmittag2": "",
        "teilnahme": null,
		"fertig":null
    },
    {
        "abend": null,
        "id": null,
        "mail": "ulf.domgoergen@bverwg.bund.de",        
        "name": "",
        "vormittag": "", "nachmittag1": "", "nachmittag2": "",
        "teilnahme": null,
		"fertig":null
    },
    {
        "abend": null,
        "id": null,
        "mail": "Elmar.Dworazik@bverwg.bund.de",        
        "name": "",
        "vormittag": "", "nachmittag1": "", "nachmittag2": "",
        "teilnahme": null,
		"fertig":null
    },
    {
        "abend": null,
        "id": null,
        "mail": "harald.doerig@bverwg.bund.de",        
        "name": "",
        "vormittag": "", "nachmittag1": "", "nachmittag2": "",
        "teilnahme": null,
		"fertig":null
    },
    {
        "abend": null,
        "id": null,
        "mail": "Kerstin.Eck@bverwg.bund.de",        
        "name": "",
        "vormittag": "", "nachmittag1": "", "nachmittag2": "",
        "teilnahme": null,
		"fertig":null
    },
    {
        "abend": null,
        "id": null,
        "mail": "anke.eggert@bverwg.bund.de",        
        "name": "",
        "vormittag": "", "nachmittag1": "", "nachmittag2": "",
        "teilnahme": null,
		"fertig":null
    },
    {
        "abend": null,
        "id": null,
        "mail": "alexander.eichhorn@bverwg.bund.de",        
        "name": "",
        "vormittag": "", "nachmittag1": "", "nachmittag2": "",
        "teilnahme": null,
		"fertig":null
    },
    {
        "abend": null,
        "id": null,
        "mail": "Silke.Ende@bverwg.bund.de",        
        "name": "",
        "vormittag": "", "nachmittag1": "", "nachmittag2": "",
        "teilnahme": null,
		"fertig":null
    },
    {
        "abend": null,
        "id": null,
        "mail": "martina.eppelt@bverwg.bund.de",        
        "name": "",
        "vormittag": "", "nachmittag1": "", "nachmittag2": "",
        "teilnahme": null,
		"fertig":null
    },
    {
        "abend": null,
        "id": null,
        "mail": "josefine.eppinger@bverwg.bund.de",        
        "name": "",
        "vormittag": "", "nachmittag1": "", "nachmittag2": "",
        "teilnahme": null,
		"fertig":null
    },
    {
        "abend": null,
        "id": null,
        "mail": "bettina.felkl-reiniger@bverwg.bund.de",        
        "name": "",
        "vormittag": "", "nachmittag1": "", "nachmittag2": "",
        "teilnahme": null,
		"fertig":null
    },
    {
        "abend": null,
        "id": null,
        "mail": "Gundula.Feller@bverwg.bund.de",        
        "name": "",
        "vormittag": "", "nachmittag1": "", "nachmittag2": "",
        "teilnahme": null,
		"fertig":null
    },
    {
        "abend": null,
        "id": null,
        "mail": "Erich.Fernstedt@bverwg.bund.de",        
        "name": "",
        "vormittag": "", "nachmittag1": "", "nachmittag2": "",
        "teilnahme": null,
		"fertig":null
    },
    {
        "abend": null,
        "id": null,
        "mail": "benjamin.fikus@bverwg.bund.de",        
        "name": "",
        "vormittag": "", "nachmittag1": "", "nachmittag2": "",
        "teilnahme": null,
		"fertig":null
    },
    {
        "abend": null,
        "id": null,
        "mail": "Daniela.Finsterbusch@bverwg.bund.de",        
        "name": "",
        "vormittag": "", "nachmittag1": "", "nachmittag2": "",
        "teilnahme": null,
		"fertig":null
    },
    {
        "abend": null,
        "id": null,
        "mail": "Iris.Fischer@bverwg.bund.de",        
        "name": "",
        "vormittag": "", "nachmittag1": "", "nachmittag2": "",
        "teilnahme": null,
		"fertig":null
    },
    {
        "abend": null,
        "id": null,
        "mail": "martin.fleuss@bverwg.bund.de",        
        "name": "",
        "vormittag": "", "nachmittag1": "", "nachmittag2": "",
        "teilnahme": null,
		"fertig":null
    },
    {
        "abend": null,
        "id": null,
        "mail": "martina.franke@bverwg.bund.de",        
        "name": "",
        "vormittag": "", "nachmittag1": "", "nachmittag2": "",
        "teilnahme": null,
		"fertig":null
    },
    {
        "abend": null,
        "id": null,
        "mail": "Uwe.Freese@bverwg.bund.de",        
        "name": "",
        "vormittag": "", "nachmittag1": "", "nachmittag2": "",
        "teilnahme": null,
		"fertig":null
    },
    {
        "abend": null,
        "id": null,
        "mail": "Eva-Christine.Frentz@bverwg.bund.de",        
        "name": "",
        "vormittag": "", "nachmittag1": "", "nachmittag2": "",
        "teilnahme": null,
		"fertig":null
    },
    {
        "abend": null,
        "id": null,
        "mail": "Anne-Kathrin.Fricke@bverwg.bund.de",        
        "name": "",
        "vormittag": "", "nachmittag1": "", "nachmittag2": "",
        "teilnahme": null,
		"fertig":null
    },
    {
        "abend": null,
        "id": null,
        "mail": "eva-maria.froehlich@bverwg.bund.de",        
        "name": "",
        "vormittag": "", "nachmittag1": "", "nachmittag2": "",
        "teilnahme": null,
		"fertig":null
    },
    {
        "abend": null,
        "id": null,
        "mail": "kathi.froehlich@bverwg.bund.de",        
        "name": "",
        "vormittag": "", "nachmittag1": "", "nachmittag2": "",
        "teilnahme": null,
		"fertig":null
    },
    {
        "abend": null,
        "id": null,
        "mail": "Stephan.Gatz@bverwg.bund.de",        
        "name": "",
        "vormittag": "", "nachmittag1": "", "nachmittag2": "",
        "teilnahme": null,
		"fertig":null
    },
    {
        "abend": null,
        "id": null,
        "mail": "Antje.Gieler@bverwg.bund.de",        
        "name": "",
        "vormittag": "", "nachmittag1": "", "nachmittag2": "",
        "teilnahme": null,
		"fertig":null
    },
    {
        "abend": null,
        "id": null,
        "mail": "Monika.Goldmann@bverwg.bund.de",        
        "name": "",
        "vormittag": "", "nachmittag1": "", "nachmittag2": "",
        "teilnahme": null,
		"fertig":null
    },
    {
        "abend": null,
        "id": null,
        "mail": "Annett.Gratias@bverwg.bund.de",        
        "name": "",
        "vormittag": "", "nachmittag1": "", "nachmittag2": "",
        "teilnahme": null,
		"fertig":null
    },
    {
        "abend": null,
        "id": null,
        "mail": "Kurt.Graulich@bverwg.bund.de",        
        "name": "",
        "vormittag": "", "nachmittag1": "", "nachmittag2": "",
        "teilnahme": null,
		"fertig":null
    },
    {
        "abend": null,
        "id": null,
        "mail": "Tilo.Graupner@bverwg.bund.de",        
        "name": "",
        "vormittag": "", "nachmittag1": "", "nachmittag2": "",
        "teilnahme": null,
		"fertig":null
    },
    {
        "abend": null,
        "id": null,
        "mail": "Gabriela.Hagedorn@bverwg.bund.de",        
        "name": "",
        "vormittag": "", "nachmittag1": "", "nachmittag2": "",
        "teilnahme": null,
		"fertig":null
    },
    {
        "abend": null,
        "id": null,
        "mail": "carsten.hahn@bverwg.bund.de",        
        "name": "",
        "vormittag": "", "nachmittag1": "", "nachmittag2": "",
        "teilnahme": null,
		"fertig":null
    },
    {
        "abend": null,
        "id": null,
        "mail": "christin.hahn@bverwg.bund.de",        
        "name": "",
        "vormittag": "", "nachmittag1": "", "nachmittag2": "",
        "teilnahme": null,
		"fertig":null
    },
    {
        "abend": null,
        "id": null,
        "mail": "Sylvia.Hardtmann@bverwg.bund.de",        
        "name": "",
        "vormittag": "", "nachmittag1": "", "nachmittag2": "",
        "teilnahme": null,
		"fertig":null
    },
    {
        "abend": null,
        "id": null,
        "mail": "katharina.harms@bverwg.bund.de",        
        "name": "",
        "vormittag": "", "nachmittag1": "", "nachmittag2": "",
        "teilnahme": null,
		"fertig":null
    },
    {
        "abend": null,
        "id": null,
        "mail": "ute.harnisch@bverwg.bund.de",        
        "name": "",
        "vormittag": "", "nachmittag1": "", "nachmittag2": "",
        "teilnahme": null,
		"fertig":null
    },
    {
        "abend": null,
        "id": null,
        "mail": "andreas.hartung@bverwg.bund.de",        
        "name": "",
        "vormittag": "", "nachmittag1": "", "nachmittag2": "",
        "teilnahme": null,
		"fertig":null
    },
    {
        "abend": null,
        "id": null,
        "mail": "jan.hecker@bverwg.bund.de",        
        "name": "",
        "vormittag": "", "nachmittag1": "", "nachmittag2": "",
        "teilnahme": null,
		"fertig":null
    },
    {
        "abend": null,
        "id": null,
        "mail": "Rene.Heger@bverwg.bund.de",        
        "name": "",
        "vormittag": "", "nachmittag1": "", "nachmittag2": "",
        "teilnahme": null,
		"fertig":null
    },
    {
        "abend": null,
        "id": null,
        "mail": "madeleine.heger@bverwg.bund.de",        
        "name": "",
        "vormittag": "", "nachmittag1": "", "nachmittag2": "",
        "teilnahme": null,
		"fertig":null
    },
    {
        "abend": null,
        "id": null,
        "mail": "sibylle.vonHeimburg@bverwg.bund.de",        
        "name": "",
        "vormittag": "", "nachmittag1": "", "nachmittag2": "",
        "teilnahme": null,
		"fertig":null
    },
    {
        "abend": null,
        "id": null,
        "mail": "Thomas.Heitz@bverwg.bund.de",        
        "name": "",
        "vormittag": "", "nachmittag1": "", "nachmittag2": "",
        "teilnahme": null,
		"fertig":null
    },
    {
        "abend": null,
        "id": null,
        "mail": "Ulla.Held-Daab@bverwg.bund.de",        
        "name": "",
        "vormittag": "", "nachmittag1": "", "nachmittag2": "",
        "teilnahme": null,
		"fertig":null
    },
    {
        "abend": null,
        "id": null,
        "mail": "johannes.henke@bverwg.bund.de",        
        "name": "",
        "vormittag": "", "nachmittag1": "", "nachmittag2": "",
        "teilnahme": null,
		"fertig":null
    },
    {
        "abend": null,
        "id": null,
        "mail": "paul.hentschel@bverwg.bund.de",        
        "name": "",
        "vormittag": "", "nachmittag1": "", "nachmittag2": "",
        "teilnahme": null,
		"fertig":null
    },
    {
        "abend": null,
        "id": null,
        "mail": "Peter.Heumann@bverwg.bund.de",        
        "name": "",
        "vormittag": "", "nachmittag1": "", "nachmittag2": "",
        "teilnahme": null,
		"fertig":null
    },
    {
        "abend": null,
        "id": null,
        "mail": "petra.hoock@bverwg.bund.de",        
        "name": "",
        "vormittag": "", "nachmittag1": "", "nachmittag2": "",
        "teilnahme": null,
		"fertig":null
    },
    {
        "abend": null,
        "id": null,
        "mail": "Thomas.Hoppe@bverwg.bund.de",        
        "name": "",
        "vormittag": "", "nachmittag1": "", "nachmittag2": "",
        "teilnahme": null,
		"fertig":null
    },
    {
        "abend": null,
        "id": null,
        "mail": "jana.haenig@bverwg.bund.de",        
        "name": "",
        "vormittag": "", "nachmittag1": "", "nachmittag2": "",
        "teilnahme": null,
		"fertig":null
    },
    {
        "abend": null,
        "id": null,
        "mail": "richard.haeussler@bverwg.bund.de",        
        "name": "",
        "vormittag": "", "nachmittag1": "", "nachmittag2": "",
        "teilnahme": null,
		"fertig":null
    },
    {
        "abend": null,
        "id": null,
        "mail": "uta.hoernicke@bverwg.bund.de",        
        "name": "",
        "vormittag": "", "nachmittag1": "", "nachmittag2": "",
        "teilnahme": null,
		"fertig":null
    },
    {
        "abend": null,
        "id": null,
        "mail": "carola.ihle@bverwg.bund.de",        
        "name": "",
        "vormittag": "", "nachmittag1": "", "nachmittag2": "",
        "teilnahme": null,
		"fertig":null
    },
    {
        "abend": null,
        "id": null,
        "mail": "Angelika.Jakob@bverwg.bund.de",        
        "name": "",
        "vormittag": "", "nachmittag1": "", "nachmittag2": "",
        "teilnahme": null,
		"fertig":null
    },
    {
        "abend": null,
        "id": null,
        "mail": "jana.jesert@bverwg.bund.de",        
        "name": "",
        "vormittag": "", "nachmittag1": "", "nachmittag2": "",
        "teilnahme": null,
		"fertig":null
    },
    {
        "abend": null,
        "id": null,
        "mail": "Uta.Kairies@bverwg.bund.de",        
        "name": "",
        "vormittag": "", "nachmittag1": "", "nachmittag2": "",
        "teilnahme": null,
		"fertig":null
    },
    {
        "abend": null,
        "id": null,
        "mail": "enrico.kallaewe@bverwg.bund.de",        
        "name": "",
        "vormittag": "", "nachmittag1": "", "nachmittag2": "",
        "teilnahme": null,
		"fertig":null
    },
    {
        "abend": null,
        "id": null,
        "mail": "antje.kasch@bverwg.bund.de",        
        "name": "",
        "vormittag": "", "nachmittag1": "", "nachmittag2": "",
        "teilnahme": null,
		"fertig":null
    },
    {
        "abend": null,
        "id": null,
        "mail": "robert.keller@bverwg.bund.de",        
        "name": "",
        "vormittag": "", "nachmittag1": "", "nachmittag2": "",
        "teilnahme": null,
		"fertig":null
    },
    {
        "abend": null,
        "id": null,
        "mail": "markus.kenntner@bverwg.bund.de",        
        "name": "",
        "vormittag": "", "nachmittag1": "", "nachmittag2": "",
        "teilnahme": null,
		"fertig":null
    },
    {
        "abend": null,
        "id": null,
        "mail": "Thomas.Kern@bverwg.bund.de",        
        "name": "",
        "vormittag": "", "nachmittag1": "", "nachmittag2": "",
        "teilnahme": null,
		"fertig":null
    },
    {
        "abend": null,
        "id": null,
        "mail": "carolin.klehr@bverwg.bund.de",        
        "name": "",
        "vormittag": "", "nachmittag1": "", "nachmittag2": "",
        "teilnahme": null,
		"fertig":null
    },
    {
        "abend": null,
        "id": null,
        "mail": "Sabine.Kleinschmidt@bverwg.bund.de",        
        "name": "",
        "vormittag": "", "nachmittag1": "", "nachmittag2": "",
        "teilnahme": null,
		"fertig":null
    },
    {
        "abend": null,
        "id": null,
        "mail": "Dieter.Kley@bverwg.bund.de",        
        "name": "",
        "vormittag": "", "nachmittag1": "", "nachmittag2": "",
        "teilnahme": null,
		"fertig":null
    },
    {
        "abend": null,
        "id": null,
        "mail": "steffi.klisch@bverwg.bund.de",        
        "name": "",
        "vormittag": "", "nachmittag1": "", "nachmittag2": "",
        "teilnahme": null,
		"fertig":null
    },
    {
        "abend": null,
        "id": null,
        "mail": "Ines.Kops@bverwg.bund.de",        
        "name": "",
        "vormittag": "", "nachmittag1": "", "nachmittag2": "",
        "teilnahme": null,
		"fertig":null
    },
    {
        "abend": null,
        "id": null,
        "mail": "andreas.korbmacher@bverwg.bund.de",        
        "name": "",
        "vormittag": "", "nachmittag1": "", "nachmittag2": "",
        "teilnahme": null,
		"fertig":null
    },
    {
        "abend": null,
        "id": null,
        "mail": "heike.kowalski@bverwg.bund.de",        
        "name": "",
        "vormittag": "", "nachmittag1": "", "nachmittag2": "",
        "teilnahme": null,
		"fertig":null
    },
    {
        "abend": null,
        "id": null,
        "mail": "Ingo.Kraft@bverwg.bund.de",        
        "name": "",
        "vormittag": "", "nachmittag1": "", "nachmittag2": "",
        "teilnahme": null,
		"fertig":null
    },
    {
        "abend": null,
        "id": null,
        "mail": "guenter.krauss@bverwg.bund.de",        
        "name": "",
        "vormittag": "", "nachmittag1": "", "nachmittag2": "",
        "teilnahme": null,
		"fertig":null
    },
    {
        "abend": null,
        "id": null,
        "mail": "kirsten.kuhlmann@bverwg.bund.de",        
        "name": "",
        "vormittag": "", "nachmittag1": "", "nachmittag2": "",
        "teilnahme": null,
		"fertig":null
    },
    {
        "abend": null,
        "id": null,
        "mail": "Steffen.Kummer@bverwg.bund.de",        
        "name": "",
        "vormittag": "", "nachmittag1": "", "nachmittag2": "",
        "teilnahme": null,
		"fertig":null
    },
    {
        "abend": null,
        "id": null,
        "mail": "uwe.kaemmler@bverwg.bund.de",        
        "name": "",
        "vormittag": "", "nachmittag1": "", "nachmittag2": "",
        "teilnahme": null,
		"fertig":null
    },
    {
        "abend": null,
        "id": null,
        "mail": "doreen.koehler@bverwg.bund.de",        
        "name": "",
        "vormittag": "", "nachmittag1": "", "nachmittag2": "",
        "teilnahme": null,
		"fertig":null
    },
    {
        "abend": null,
        "id": null,
        "mail": "christoph.kuelpmann@bverwg.bund.de",        
        "name": "",
        "vormittag": "", "nachmittag1": "", "nachmittag2": "",
        "teilnahme": null,
		"fertig":null
    },
    {
        "abend": null,
        "id": null,
        "mail": "Stefan.Langer@bverwg.bund.de",        
        "name": "",
        "vormittag": "", "nachmittag1": "", "nachmittag2": "",
        "teilnahme": null,
		"fertig":null
    },
    {
        "abend": null,
        "id": null,
        "mail": "Jens.Langpeter@bverwg.bund.de",        
        "name": "",
        "vormittag": "", "nachmittag1": "", "nachmittag2": "",
        "teilnahme": null,
		"fertig":null
    },
    {
        "abend": null,
        "id": null,
        "mail": "madeleine.lehmann@bverwg.bund.de",        
        "name": "",
        "vormittag": "", "nachmittag1": "", "nachmittag2": "",
        "teilnahme": null,
		"fertig":null
    },
    {
        "abend": null,
        "id": null,
        "mail": "Stefan.Liebler@bverwg.bund.de",        
        "name": "",
        "vormittag": "", "nachmittag1": "", "nachmittag2": "",
        "teilnahme": null,
		"fertig":null
    },
    {
        "abend": null,
        "id": null,
        "mail": "Petra.Lubitz@bverwg.bund.de",        
        "name": "",
        "vormittag": "", "nachmittag1": "", "nachmittag2": "",
        "teilnahme": null,
		"fertig":null
    },
    {
        "abend": null,
        "id": null,
        "mail": "Thomas.Mai@bverwg.bund.de",        
        "name": "",
        "vormittag": "", "nachmittag1": "", "nachmittag2": "",
        "teilnahme": null,
		"fertig":null
    },
    {
        "abend": null,
        "id": null,
        "mail": "Janet.Melzer@bverwg.bund.de",        
        "name": "",
        "vormittag": "", "nachmittag1": "", "nachmittag2": "",
        "teilnahme": null,
		"fertig":null
    },
    {
        "abend": null,
        "id": null,
        "mail": "sebastian.meyer@bverwg.bund.de",        
        "name": "",
        "vormittag": "", "nachmittag1": "", "nachmittag2": "",
        "teilnahme": null,
		"fertig":null
    },
    {
        "abend": null,
        "id": null,
        "mail": "knut.moeller@bverwg.bund.de",        
        "name": "",
        "vormittag": "", "nachmittag1": "", "nachmittag2": "",
        "teilnahme": null,
		"fertig":null
    },
    {
        "abend": null,
        "id": null,
        "mail": "lorenz.muehling@bverwg.bund.de",        
        "name": "",
        "vormittag": "", "nachmittag1": "", "nachmittag2": "",
        "teilnahme": null,
		"fertig":null
    },
    {
        "abend": null,
        "id": null,
        "mail": "baerbel.mueller@bverwg.bund.de",        
        "name": "",
        "vormittag": "", "nachmittag1": "", "nachmittag2": "",
        "teilnahme": null,
		"fertig":null
    },
    {
        "abend": null,
        "id": null,
        "mail": "vicki.mueller@bverwg.bund.de",        
        "name": "",
        "vormittag": "", "nachmittag1": "", "nachmittag2": "",
        "teilnahme": null,
		"fertig":null
    },
    {
        "abend": null,
        "id": null,
        "mail": "Werner.Neumann@bverwg.bund.de",        
        "name": "",
        "vormittag": "", "nachmittag1": "", "nachmittag2": "",
        "teilnahme": null,
		"fertig":null
    },
    {
        "abend": null,
        "id": null,
        "mail": "ruediger.nolte@bverwg.bund.de",        
        "name": "",
        "vormittag": "", "nachmittag1": "", "nachmittag2": "",
        "teilnahme": null,
		"fertig":null
    },
    {
        "abend": null,
        "id": null,
        "mail": "Ina.Oertel@bverwg.bund.de",        
        "name": "",
        "vormittag": "", "nachmittag1": "", "nachmittag2": "",
        "teilnahme": null,
		"fertig":null
    },
    {
        "abend": null,
        "id": null,
        "mail": "kathleen.ordnung@bverwg.bund.de",        
        "name": "",
        "vormittag": "", "nachmittag1": "", "nachmittag2": "",
        "teilnahme": null,
		"fertig":null
    },
    {
        "abend": null,
        "id": null,
        "mail": "katja.ott@bverwg.bund.de",        
        "name": "",
        "vormittag": "", "nachmittag1": "", "nachmittag2": "",
        "teilnahme": null,
		"fertig":null
    },
    {
        "abend": null,
        "id": null,
        "mail": "Alexandra.Ott@bverwg.bund.de",        
        "name": "",
        "vormittag": "", "nachmittag1": "", "nachmittag2": "",
        "teilnahme": null,
		"fertig":null
    },
    {
        "abend": null,
        "id": null,
        "mail": "Bernd.Patitz@bverwg.bund.de",        
        "name": "",
        "vormittag": "", "nachmittag1": "", "nachmittag2": "",
        "teilnahme": null,
		"fertig":null
    },
    {
        "abend": null,
        "id": null,
        "mail": "helmut.petz@bverwg.bund.de",        
        "name": "",
        "vormittag": "", "nachmittag1": "", "nachmittag2": "",
        "teilnahme": null,
		"fertig":null
    },
    {
        "abend": null,
        "id": null,
        "mail": "ines.petzold@bverwg.bund.de",        
        "name": "",
        "vormittag": "", "nachmittag1": "", "nachmittag2": "",
        "teilnahme": null,
		"fertig":null
    },
    {
        "abend": null,
        "id": null,
        "mail": "Renate.Philipp@bverwg.bund.de",        
        "name": "",
        "vormittag": "", "nachmittag1": "", "nachmittag2": "",
        "teilnahme": null,
		"fertig":null
    },
    {
        "abend": null,
        "id": null,
        "mail": "sebastian.pilz@bverwg.bund.de",        
        "name": "",
        "vormittag": "", "nachmittag1": "", "nachmittag2": "",
        "teilnahme": null,
		"fertig":null
    },
    {
        "abend": null,
        "id": null,
        "mail": "juergen.preiss@bverwg.bund.de",        
        "name": "",
        "vormittag": "", "nachmittag1": "", "nachmittag2": "",
        "teilnahme": null,
		"fertig":null
    },
    {
        "abend": null,
        "id": null,
        "mail": "kerstin.prekel@bverwg.bund.de",        
        "name": "",
        "vormittag": "", "nachmittag1": "", "nachmittag2": "",
        "teilnahme": null,
		"fertig":null
    },
    {
        "abend": null,
        "id": null,
        "mail": "Christiane.Radke@bverwg.bund.de",        
        "name": "",
        "vormittag": "", "nachmittag1": "", "nachmittag2": "",
        "teilnahme": null,
		"fertig":null
    },
    {
        "abend": null,
        "id": null,
        "mail": "Mario.Reiche@bverwg.bund.de",        
        "name": "",
        "vormittag": "", "nachmittag1": "", "nachmittag2": "",
        "teilnahme": null,
		"fertig":null
    },
    {
        "abend": null,
        "id": null,
        "mail": "Margot.Reinhardt@bverwg.bund.de",        
        "name": "",
        "vormittag": "", "nachmittag1": "", "nachmittag2": "",
        "teilnahme": null,
		"fertig":null
    },
    {
        "abend": null,
        "id": null,
        "mail": "denise.renger@bverwg.bund.de",        
        "name": "",
        "vormittag": "", "nachmittag1": "", "nachmittag2": "",
        "teilnahme": null,
		"fertig":null
    },
    {
        "abend": null,
        "id": null,
        "mail": "christin.renner@bverwg.bund.de",        
        "name": "",
        "vormittag": "", "nachmittag1": "", "nachmittag2": "",
        "teilnahme": null,
		"fertig":null
    },
    {
        "abend": null,
        "id": null,
        "mail": "Klaus.Rennert@bverwg.bund.de",        
        "name": "",
        "vormittag": "", "nachmittag1": "", "nachmittag2": "",
        "teilnahme": null,
		"fertig":null
    },
    {
        "abend": null,
        "id": null,
        "mail": "Gabriele.Richter@bverwg.bund.de",        
        "name": "",
        "vormittag": "", "nachmittag1": "", "nachmittag2": "",
        "teilnahme": null,
		"fertig":null
    },
    {
        "abend": null,
        "id": null,
        "mail": "Matthias.Richter@bverwg.bund.de",        
        "name": "",
        "vormittag": "", "nachmittag1": "", "nachmittag2": "",
        "teilnahme": null,
		"fertig":null
    },
    {
        "abend": null,
        "id": null,
        "mail": "Karsten.Rosche@bverwg.bund.de",        
        "name": "",
        "vormittag": "", "nachmittag1": "", "nachmittag2": "",
        "teilnahme": null,
		"fertig":null
    },
    {
        "abend": null,
        "id": null,
        "mail": "TillOliver.Rothfuss@bverwg.bund.de",        
        "name": "",
        "vormittag": "", "nachmittag1": "", "nachmittag2": "",
        "teilnahme": null,
		"fertig":null
    },
    {
        "abend": null,
        "id": null,
        "mail": "ruediger.rubel@bverwg.bund.de",        
        "name": "",
        "vormittag": "", "nachmittag1": "", "nachmittag2": "",
        "teilnahme": null,
		"fertig":null
    },
    {
        "abend": null,
        "id": null,
        "mail": "susanne.rublack@bverwg.bund.de",        
        "name": "",
        "vormittag": "", "nachmittag1": "", "nachmittag2": "",
        "teilnahme": null,
		"fertig":null
    },
    {
        "abend": null,
        "id": null,
        "mail": "julien.rudolph@bverwg.bund.de",        
        "name": "",
        "vormittag": "", "nachmittag1": "", "nachmittag2": "",
        "teilnahme": null,
		"fertig":null
    },
    {
        "abend": null,
        "id": null,
        "mail": "inge.rudolph@bverwg.bund.de",        
        "name": "",
        "vormittag": "", "nachmittag1": "", "nachmittag2": "",
        "teilnahme": null,
		"fertig":null
    },
    {
        "abend": null,
        "id": null,
        "mail": "brigitte.roeder@bverwg.bund.de",        
        "name": "",
        "vormittag": "", "nachmittag1": "", "nachmittag2": "",
        "teilnahme": null,
		"fertig":null
    },
    {
        "abend": null,
        "id": null,
        "mail": "ina.rueger@bverwg.bund.de",        
        "name": "",
        "vormittag": "", "nachmittag1": "", "nachmittag2": "",
        "teilnahme": null,
		"fertig":null
    },
    {
        "abend": null,
        "id": null,
        "mail": "Jacqueline.Salli-Jarosch@bverwg.bund.de",        
        "name": "",
        "vormittag": "", "nachmittag1": "", "nachmittag2": "",
        "teilnahme": null,
		"fertig":null
    },
    {
        "abend": null,
        "id": null,
        "mail": "dirk.sander@bverwg.bund.de",        
        "name": "",
        "vormittag": "", "nachmittag1": "", "nachmittag2": "",
        "teilnahme": null,
		"fertig":null
    },
    {
        "abend": null,
        "id": null,
        "mail": "poststelle.scanner@bverwg.bund.de",        
        "name": "",
        "vormittag": "", "nachmittag1": "", "nachmittag2": "",
        "teilnahme": null,
		"fertig":null
    },
    {
        "abend": null,
        "id": null,
        "mail": "katrin.scheffler@bverwg.bund.de",        
        "name": "",
        "vormittag": "", "nachmittag1": "", "nachmittag2": "",
        "teilnahme": null,
		"fertig":null
    },
    {
        "abend": null,
        "id": null,
        "mail": "Stefan.Scherer@bverwg.bund.de",        
        "name": "",
        "vormittag": "", "nachmittag1": "", "nachmittag2": "",
        "teilnahme": null,
		"fertig":null
    },
    {
        "abend": null,
        "id": null,
        "mail": "kerstin.schipper@bverwg.bund.de",        
        "name": "",
        "vormittag": "", "nachmittag1": "", "nachmittag2": "",
        "teilnahme": null,
		"fertig":null
    },
    {
        "abend": null,
        "id": null,
        "mail": "Torsten.Schleinitz@bverwg.bund.de",        
        "name": "",
        "vormittag": "", "nachmittag1": "", "nachmittag2": "",
        "teilnahme": null,
		"fertig":null
    },
    {
        "abend": null,
        "id": null,
        "mail": "Ralph.Schlensog@bverwg.bund.de",        
        "name": "",
        "vormittag": "", "nachmittag1": "", "nachmittag2": "",
        "teilnahme": null,
		"fertig":null
    },
    {
        "abend": null,
        "id": null,
        "mail": "Michael.Schmidt@bverwg.bund.de",        
        "name": "",
        "vormittag": "", "nachmittag1": "", "nachmittag2": "",
        "teilnahme": null,
		"fertig":null
    },
    {
        "abend": null,
        "id": null,
        "mail": "Silvia.Schmidt@bverwg.bund.de",        
        "name": "",
        "vormittag": "", "nachmittag1": "", "nachmittag2": "",
        "teilnahme": null,
		"fertig":null
    },
    {
        "abend": null,
        "id": null,
        "mail": "sybille.schmidt@bverwg.bund.de",        
        "name": "",
        "vormittag": "", "nachmittag1": "", "nachmittag2": "",
        "teilnahme": null,
		"fertig":null
    },
    {
        "abend": null,
        "id": null,
        "mail": "claudia.scholz@bverwg.bund.de",        
        "name": "",
        "vormittag": "", "nachmittag1": "", "nachmittag2": "",
        "teilnahme": null,
		"fertig":null
    },
    {
        "abend": null,
        "id": null,
        "mail": "doreen.scholz@bverwg.bund.de",        
        "name": "",
        "vormittag": "", "nachmittag1": "", "nachmittag2": "",
        "teilnahme": null,
		"fertig":null
    },
    {
        "abend": null,
        "id": null,
        "mail": "marit.schroeter@bverwg.bund.de",        
        "name": "",
        "vormittag": "", "nachmittag1": "", "nachmittag2": "",
        "teilnahme": null,
		"fertig":null
    },
    {
        "abend": null,
        "id": null,
        "mail": "heike.schwarze@bverwg.bund.de",        
        "name": "",
        "vormittag": "", "nachmittag1": "", "nachmittag2": "",
        "teilnahme": null,
		"fertig":null
    },
    {
        "abend": null,
        "id": null,
        "mail": "Heiko.Schwotzer@bverwg.bund.de",        
        "name": "",
        "vormittag": "", "nachmittag1": "", "nachmittag2": "",
        "teilnahme": null,
		"fertig":null
    },
    {
        "abend": null,
        "id": null,
        "mail": "birgit.schuenemann@bverwg.bund.de",        
        "name": "",
        "vormittag": "", "nachmittag1": "", "nachmittag2": "",
        "teilnahme": null,
		"fertig":null
    },
    {
        "abend": null,
        "id": null,
        "mail": "mandy.schueritz@bverwg.bund.de",        
        "name": "",
        "vormittag": "", "nachmittag1": "", "nachmittag2": "",
        "teilnahme": null,
		"fertig":null
    },
    {
        "abend": null,
        "id": null,
        "mail": "grit.schuetz@bverwg.bund.de",        
        "name": "",
        "vormittag": "", "nachmittag1": "", "nachmittag2": "",
        "teilnahme": null,
		"fertig":null
    },
    {
        "abend": null,
        "id": null,
        "mail": "petra.schuetze@bverwg.bund.de",        
        "name": "",
        "vormittag": "", "nachmittag1": "", "nachmittag2": "",
        "teilnahme": null,
		"fertig":null
    },
    {
        "abend": null,
        "id": null,
        "mail": "Yvonne.Spengler@bverwg.bund.de",        
        "name": "",
        "vormittag": "", "nachmittag1": "", "nachmittag2": "",
        "teilnahme": null,
		"fertig":null
    },
    {
        "abend": null,
        "id": null,
        "mail": "Marco.Sprengel@bverwg.bund.de",        
        "name": "",
        "vormittag": "", "nachmittag1": "", "nachmittag2": "",
        "teilnahme": null,
		"fertig":null
    },
    {
        "abend": null,
        "id": null,
        "mail": "monika.stach@bverwg.bund.de",        
        "name": "",
        "vormittag": "", "nachmittag1": "", "nachmittag2": "",
        "teilnahme": null,
		"fertig":null
    },
    {
        "abend": null,
        "id": null,
        "mail": "martin.steinkuehler@bverwg.bund.de",        
        "name": "",
        "vormittag": "", "nachmittag1": "", "nachmittag2": "",
        "teilnahme": null,
		"fertig":null
    },
    {
        "abend": null,
        "id": null,
        "mail": "heidi.stengelhofen@bverwg.bund.de",        
        "name": "",
        "vormittag": "", "nachmittag1": "", "nachmittag2": "",
        "teilnahme": null,
		"fertig":null
    },
    {
        "abend": null,
        "id": null,
        "mail": "Jan.Stowasser@bverwg.bund.de",        
        "name": "",
        "vormittag": "", "nachmittag1": "", "nachmittag2": "",
        "teilnahme": null,
		"fertig":null
    },
    {
        "abend": null,
        "id": null,
        "mail": "Susanne.Strauch@bverwg.bund.de",        
        "name": "",
        "vormittag": "", "nachmittag1": "", "nachmittag2": "",
        "teilnahme": null,
		"fertig":null
    },
    {
        "abend": null,
        "id": null,
        "mail": "joerg.strauch@bverwg.bund.de",        
        "name": "",
        "vormittag": "", "nachmittag1": "", "nachmittag2": "",
        "teilnahme": null,
		"fertig":null
    },
    {
        "abend": null,
        "id": null,
        "mail": "rainer.stoermer@bverwg.bund.de",        
        "name": "",
        "vormittag": "", "nachmittag1": "", "nachmittag2": "",
        "teilnahme": null,
		"fertig":null
    },
    {
        "abend": null,
        "id": null,
        "mail": "Antje.Tauchert-Lindner@bverwg.bund.de",        
        "name": "",
        "vormittag": "", "nachmittag1": "", "nachmittag2": "",
        "teilnahme": null,
		"fertig":null
    },
    {
        "abend": null,
        "id": null,
        "mail": "Karin.Theil@bverwg.bund.de",        
        "name": "",
        "vormittag": "", "nachmittag1": "", "nachmittag2": "",
        "teilnahme": null,
		"fertig":null
    },
    {
        "abend": null,
        "id": null,
        "mail": "Yvonne.Thiele@bverwg.bund.de",        
        "name": "",
        "vormittag": "", "nachmittag1": "", "nachmittag2": "",
        "teilnahme": null,
		"fertig":null
    },
    {
        "abend": null,
        "id": null,
        "mail": "Anja.Thierbach@bverwg.bund.de",        
        "name": "",
        "vormittag": "", "nachmittag1": "", "nachmittag2": "",
        "teilnahme": null,
		"fertig":null
    },
    {
        "abend": null,
        "id": null,
        "mail": "florian.thurm@bverwg.bund.de",        
        "name": "",
        "vormittag": "", "nachmittag1": "", "nachmittag2": "",
        "teilnahme": null,
		"fertig":null
    },
    {
        "abend": null,
        "id": null,
        "mail": "regina.thoene@bverwg.bund.de",        
        "name": "",
        "vormittag": "", "nachmittag1": "", "nachmittag2": "",
        "teilnahme": null,
		"fertig":null
    },
    {
        "abend": null,
        "id": null,
        "mail": "margitta.toepfer@bverwg.bund.de",        
        "name": "",
        "vormittag": "", "nachmittag1": "", "nachmittag2": "",
        "teilnahme": null,
		"fertig":null
    },
    {
        "abend": null,
        "id": null,
        "mail": "buerovl@bverwg.bund.de",        
        "name": "",
        "vormittag": "", "nachmittag1": "", "nachmittag2": "",
        "teilnahme": null,
		"fertig":null
    },
    {
        "abend": null,
        "id": null,
        "mail": "Rene.Volkmer@bverwg.bund.de",        
        "name": "",
        "vormittag": "", "nachmittag1": "", "nachmittag2": "",
        "teilnahme": null,
		"fertig":null
    },
    {
        "abend": null,
        "id": null,
        "mail": "juergen.vormeier@bverwg.bund.de",        
        "name": "",
        "vormittag": "", "nachmittag1": "", "nachmittag2": "",
        "teilnahme": null,
		"fertig":null
    },
    {
        "abend": null,
        "id": null,
        "mail": "kathrin.voelkel@bverwg.bund.de",        
        "name": "",
        "vormittag": "", "nachmittag1": "", "nachmittag2": "",
        "teilnahme": null,
		"fertig":null
    },
    {
        "abend": null,
        "id": null,
        "mail": "monika.voellmann@bverwg.bund.de",        
        "name": "",
        "vormittag": "", "nachmittag1": "", "nachmittag2": "",
        "teilnahme": null,
		"fertig":null
    },
    {
        "abend": null,
        "id": null,
        "mail": "Claudia.Wahl@bverwg.bund.de",        
        "name": "",
        "vormittag": "", "nachmittag1": "", "nachmittag2": "",
        "teilnahme": null,
		"fertig":null
    },
    {
        "abend": null,
        "id": null,
        "mail": "claudia.wallberg@bverwg.bund.de",        
        "name": "",
        "vormittag": "", "nachmittag1": "", "nachmittag2": "",
        "teilnahme": null,
		"fertig":null
    },
    {
        "abend": null,
        "id": null,
        "mail": "timo.walter@bverwg.bund.de",        
        "name": "",
        "vormittag": "", "nachmittag1": "", "nachmittag2": "",
        "teilnahme": null,
		"fertig":null
    },
    {
        "abend": null,
        "id": null,
        "mail": "Holger.Wartmann@bverwg.bund.de",        
        "name": "",
        "vormittag": "", "nachmittag1": "", "nachmittag2": "",
        "teilnahme": null,
		"fertig":null
    },
    {
        "abend": null,
        "id": null,
        "mail": "benjamin.weber@bverwg.bund.de",        
        "name": "",
        "vormittag": "", "nachmittag1": "", "nachmittag2": "",
        "teilnahme": null,
		"fertig":null
    },
    {
        "abend": null,
        "id": null,
        "mail": "thomas.weber@bverwg.bund.de",        
        "name": "",
        "vormittag": "", "nachmittag1": "", "nachmittag2": "",
        "teilnahme": null,
		"fertig":null
    },
    {
        "abend": null,
        "id": null,
        "mail": "Klaus.Weidenvonder@bverwg.bund.de",        
        "name": "",
        "vormittag": "", "nachmittag1": "", "nachmittag2": "",
        "teilnahme": null,
		"fertig":null
    },
    {
        "abend": null,
        "id": null,
        "mail": "Gabriela.Weikinnis@bverwg.bund.de",        
        "name": "",
        "vormittag": "", "nachmittag1": "", "nachmittag2": "",
        "teilnahme": null,
		"fertig":null
    },
    {
        "abend": null,
        "id": null,
        "mail": "renate.wenninger@bverwg.bund.de",        
        "name": "",
        "vormittag": "", "nachmittag1": "", "nachmittag2": "",
        "teilnahme": null,
		"fertig":null
    },
    {
        "abend": null,
        "id": null,
        "mail": "Silke.Werner@bverwg.bund.de",        
        "name": "",
        "vormittag": "", "nachmittag1": "", "nachmittag2": "",
        "teilnahme": null,
		"fertig":null
    },
    {
        "abend": null,
        "id": null,
        "mail": "susan.werner@bverwg.bund.de",        
        "name": "",
        "vormittag": "", "nachmittag1": "", "nachmittag2": "",
        "teilnahme": null,
		"fertig":null
    },
    {
        "abend": null,
        "id": null,
        "mail": "nico.weyer@bverwg.bund.de",        
        "name": "",
        "vormittag": "", "nachmittag1": "", "nachmittag2": "",
        "teilnahme": null,
		"fertig":null
    },
    {
        "abend": null,
        "id": null,
        "mail": "Petra.Willich@bverwg.bund.de",        
        "name": "",
        "vormittag": "", "nachmittag1": "", "nachmittag2": "",
        "teilnahme": null,
		"fertig":null
    },
    {
        "abend": null,
        "id": null,
        "mail": "franziska.wolf@bverwg.bund.de",        
        "name": "",
        "vormittag": "", "nachmittag1": "", "nachmittag2": "",
        "teilnahme": null,
		"fertig":null
    },
    {
        "abend": null,
        "id": null,
        "mail": "steffi.wolframm@bverwg.bund.de",        
        "name": "",
        "vormittag": "", "nachmittag1": "", "nachmittag2": "",
        "teilnahme": null,
		"fertig":null
    },
    {
        "abend": null,
        "id": null,
        "mail": "Silvia.Wowk@bverwg.bund.de",        
        "name": "",
        "vormittag": "", "nachmittag1": "", "nachmittag2": "",
        "teilnahme": null,
		"fertig":null
    },
    {
        "abend": null,
        "id": null,
        "mail": "peter.wysk@bverwg.bund.de",        
        "name": "",
        "vormittag": "", "nachmittag1": "", "nachmittag2": "",
        "teilnahme": null,
		"fertig":null
    },
    {
        "abend": null,
        "id": null,
        "mail": "holger.woeckel@bverwg.bund.de",        
        "name": "",
        "vormittag": "", "nachmittag1": "", "nachmittag2": "",
        "teilnahme": null,
		"fertig":null
    },
    {
        "abend": null,
        "id": null,
        "mail": "Heidi.Zein@bverwg.bund.de",        
        "name": "",
        "vormittag": "", "nachmittag1": "", "nachmittag2": "",
        "teilnahme": null,
		"fertig":null
    },
    {
        "abend": null,
        "id": null,
        "mail": "Monika.Ziebarth@bverwg.bund.de",        
        "name": "",
        "vormittag": "", "nachmittag1": "", "nachmittag2": "",
        "teilnahme": null,
		"fertig":null
    },
    {
        "abend": null,
        "id": null,
        "mail": "Silvana.Zweigler@bverwg.bund.de",        
        "name": "",
        "vormittag": "", "nachmittag1": "", "nachmittag2": "",
        "teilnahme": null,
		"fertig":null
    },
    {
        "abend": null,
        "id": null,
        "mail": "beate.vanderMeer@bverwg.bund.de",        
        "name": "",
        "vormittag": "", "nachmittag1": "", "nachmittag2": "",
        "teilnahme": null,
		"fertig":null
    },
    {
        "abend": null,
        "id": null,
        "mail": "desiree.vonFoerster@bverwg.bund.de",        
        "name": "",
        "vormittag": "", "nachmittag1": "", "nachmittag2": "",
        "teilnahme": null,
		"fertig":null
    },
    {
        "abend": null,
        "id": null,
        "mail": "schoene@bverwg.bund.de",        
        "name": "",
        "vormittag": "", "nachmittag1": "", "nachmittag2": "",
        "teilnahme": null,
		"fertig":null
    },
    {
        "abend": null,
        "id": null,
        "mail": "alter@bverwg.bund.de",        
        "name": "",
        "vormittag": "", "nachmittag1": "", "nachmittag2": "",
        "teilnahme": null,
		"fertig":null
    },
    {
        "abend": null,
        "id": null,
        "mail": "guenther@bverwg.bund.de",        
        "name": "",
        "vormittag": "", "nachmittag1": "", "nachmittag2": "",
        "teilnahme": null,
		"fertig":null
    },
    {
        "abend": null,
        "id": null,
        "mail": "schemmer@bverwg.bund.de",        
        "name": "",
        "vormittag": "", "nachmittag1": "", "nachmittag2": "",
        "teilnahme": null,
		"fertig":null
    }
]